LICENSE
MANIFEST.in
README.rst
setup.cfg
setup.py
snakecharmer/__init__.py
snakecharmer/__main__.py
snakecharmer/binaries.py
snakecharmer/files_formats.py
snakecharmer.egg-info/PKG-INFO
snakecharmer.egg-info/SOURCES.txt
snakecharmer.egg-info/dependency_links.txt
snakecharmer.egg-info/entry_points.txt
snakecharmer.egg-info/requires.txt
snakecharmer.egg-info/top_level.txt
snakecharmer.egg-info/zip-safe