Metadata-Version: 1.1
Name: snakecharmer
Version: 0.1.dev4
Summary: Helper functions for Snakemake genomics pipelines
Home-page: https://github.com/LankyCyril/snakeknot
Author: Kirill Grigorev
Author-email: UNKNOWN
License: MIT
Platform: UNKNOWN
Classifier: Development Status :: 3 - Alpha
Classifier: Programming Language :: Python :: 3
Classifier: Environment :: Console
Classifier: License :: OSI Approved :: MIT License
Classifier: Intended Audience :: Developers
Classifier: Topic :: Software Development :: Libraries :: Application Frameworks
